{
    "Job_Catagory":[{"Sector":"Accountancy"},{"Sector":"Administrative"},{"Sector":"Agriculture"},{"Sector":"Architectural Services"},
	  {"Sector":"Arts & Entertainment"} , {"Sector":"Automotive"} , {"Sector":"Banking"} , {"Sector":"Biotec/Pharm"} , {"Sector":"Construction"} ,
	  {"Sector":"Consulting"},{"Sector":"Customer Service"},{"Sector":"Design"},{"Sector":"Education"},{"Sector":"Energy"},{"Sector":"Engineering"},
	  {"Sector":"	Finance"},{"Sector":"Government/Non-Profit"},{"Sector":"Healthcare"},{"Sector":"Hospitality"},{"Sector":"Information Technology"},
	  {"Sector":"Internet"}, {"Sector":"Legal Services"}, {"Sector":"Leisure"},  {"Sector":"Logistics"},{"Sector":"Manufacturing"},
	  {"Sector":"Marketing & PR"}, {"Sector":"Procurement"}, {"Sector":"Property"}, {"Sector":"	Recruitment/HR"},{"Sector":"Retail"},
	  {"Sector":"Other"} ,{"Sector":"Transition Services"},{"Sector":"Tourism"},{"Sector":"Telecommunication"},
	  {"Sector":"Technical"},{"Sector":"Science"},{"Sector":"Sales"}


],
  "Skill":[
	{"Name": "Java "  },
	{"Name": "ModelBased"},
	{"Name": "C#"},
	{"Name": "C++"},
	{"Name": "Web Design"},
	{"Name": "Control Programing"  },
	{"Name": "Testing " }
  ],
    "Company_2":[
    	{"Name": "FIAT",  "Sector": "Computer", "Tittle": "control engineer","Detail": "Show Datail Show DatailShow DatailShow DatailShow DatailShow DatailShow Datail"},
    	{"Name": "GULF",  "Sector": "Industy", "Tittle": "control engineer","Detail": "Show Datail"},
    	{"Name": "ABB",  "Sector": "IT", "Tittle": "Computer engineer","Detail": "Show Datail"},
    	{"Name": "ABB",  "Sector": "Industy", "Tittle": "control engineer","Detail": "Show Datail"},
    	{"Name": "XX.PLC",  "Sector": "Accounting", "Tittle": "Accountant","Detail": "Show Datail"},
    	{"Name": "ABB",  "Sector": "Industy", "Tittle": "control engineer","Detail": "Show Datail"},
        {"Name": "Polito",  "Sector": "IT", "Tittle": "Software engineer","Detail": "Show Datail"}
    ],
  "Inbox": [
	{
	  "id": "1",
	  "From": "dine@gmail.com",
	  "subject": "Movie Tickets Confirmation..",
	  "message" : "Tutorial about combing Android Tabview and ListView",
	  "date": "May 22"
	},
	{
	  "id": "2",
	  "From": "william@gmail.com",
	  "subject": "Project estimataion details",
	  "message" : "Tutorial about combing Android Tabview and ListView",
	  "date": "May 21"
	},
	{
	  "id": "3",
	  "From": "google@gmail.com",
	  "subject": "Feedback about gmail tasks",
	  "message" : "Tutorial about combing Android Tabview and ListView",
	  "date": "May 15"
	},
	{
	  "id": "4",
	  "From": "facebook@fb.com",
	  "subject": "API Documentation not found",
	  "message" : "Tutorial about combing Android Tabview and ListView",
	  "date": "May 14"
	},
	{
	  "id": "5",
	  "From": "hdfc@hdfc.com",
	  "subject": "Request to change address",
	  "message" : "Tutorial about combing Android Tabview and ListView",
	  "date": "May 11"
	},
	{
	  "id": "6",
	  "From": "notepad@gmail.com",
	  "subject": "New version released",
	  "message" : "Tutorial about combing Android Tabview and ListView",
	  "date": "May 10"
	},
	{
	  "id": "7",
	  "From": "netbeans@sun.com",
	  "subject": "Netbeans theme development",
	  "message" : "Tutorial about combing Android Tabview and ListView",
	  "date": "April 25"
	},
	{
	  "id": "8",
	  "From": "android@google.com",
	  "subject": "New SDK downloading problem",
	  "message" : "Tutorial about combing Android Tabview and ListView",
	  "date": "April 20"
	}
  ]
}

